dictdatabase/__init__.py
dictdatabase/byte_codes.py
dictdatabase/configuration.py
dictdatabase/indexing.py
dictdatabase/io_bytes.py
dictdatabase/io_safe.py
dictdatabase/io_unsafe.py
dictdatabase/locking.py
dictdatabase/models.py
dictdatabase/sessions.py
dictdatabase/utils.py
dictdatabase-2.5.1.dist-info/METADATA
dictdatabase-2.5.1.dist-info/WHEEL
dictdatabase-2.5.1.dist-info/top_level.txt
dictdatabase-2.5.1.dist-info/RECORD
