Metadata-Version: 2.4
Name: dictdatabase
Version: 2.5.1
Summary: Easy-to-use database using dicts
Author-email: Marcel Kröker <kroeker.marcel@gmail.com>
License: MIT License
Classifier: Programming Language :: Python :: 3
Classifier: License :: OSI Approved :: MIT License
Classifier: Operating System :: OS Independent
Classifier: Intended Audience :: Developers
Classifier: Programming Language :: Python
Classifier: Topic :: Software Development :: Libraries :: Python Modules
Requires-Python: <3.14,>=3.8
Requires-Dist: orjson<4.0,>=3.9
